{
    "$schema": "http://json-schema.org/draft-04/schema#",
    "$ref": "#/definitions/MsgCreatePerpetualCloseOrder",
    "definitions": {
        "MsgCreatePerpetualCloseOrder": {
            "properties": {
                "owner_address": {
                    "type": "string"
                },
                "legacy_trigger_price_v1": {
                    "$ref": "#/definitions/elys.tradeshield.LegacyTriggerPriceV1",
                    "additionalProperties": false
                },
                "trigger_price": {
                    "type": "string"
                },
                "position_id": {
                    "type": "string"
                }
            },
            "additionalProperties": false,
            "type": "object",
            "title": "Msg Create Perpetual Close Order"
        },
        "elys.tradeshield.LegacyTriggerPriceV1": {
            "properties": {
                "trading_asset_denom": {
                    "type": "string"
                },
                "rate": {
                    "type": "string"
                }
            },
            "additionalProperties": false,
            "type": "object",
            "title": "Legacy Trigger Price V 1"
        }
    }
}