{
  "$ref": "#/definitions/MsgUpdateEnabledPools",
  "definitions": {
    "MsgUpdateEnabledPools": {
      "properties": {
        "authority": {
          "type": "string",
          "description": "authority is the address that controls the module (defaults to x/gov unless overwritten)."
        },
        "enabledPools": {
          "items": {
            "type": "string"
          },
          "type": "array"
        }
      },
      "additionalProperties": false,
      "type": "object",
      "title": "Msg Update Enabled Pools"
    }
  }
}
